{
  "comment": "JLCPCB rotation correction offsets in degrees. Add this to KiCad rotation to get correct JLCPCB rotation.",
  "offsets": {
    "SOT-23":       180,
    "SOT-23-3":     180,
    "SOT-23-5":     180,
    "SOT-23-6":     180,
    "SOT-323":      180,
    "SOT-363":      180,
    "SOT-89":       180,
    "SOT-223":      180,
    "SOT-563":      180,
    "SC-70":        180,
    "SC-88":        180,
    "TSSOP-8":      180,
    "TSSOP-14":     180,
    "TSSOP-16":     180,
    "TSSOP-20":     180,
    "TSSOP-24":     180,
    "TSSOP-28":     180,
    "SOIC-8":       180,
    "SOIC-14":      180,
    "SOIC-16":      180,
    "SOP-8":        180,
    "SOP-16":       180,
    "SSOP-16":      180,
    "SSOP-20":      180,
    "SSOP-24":      180,
    "QFN-16":       270,
    "QFN-20":       270,
    "QFN-24":       270,
    "QFN-28":       270,
    "QFN-32":       270,
    "QFN-48":       270,
    "QFN-64":       270,
    "LQFP-32":      270,
    "LQFP-48":      270,
    "LQFP-64":      270,
    "LQFP-100":     270,
    "TQFP-32":      270,
    "TQFP-48":      270,
    "TQFP-64":      270,
    "DFN-6":        270,
    "DFN-8":        270,
    "DFN-10":       270,
    "TO-252":       180,
    "TO-263":       180,
    "DPAK":         180,
    "D2PAK":        180,
    "0402":         0,
    "0603":         0,
    "0805":         0,
    "1206":         0,
    "1210":         0,
    "2010":         0,
    "2512":         0,
    "LED_0603":     0,
    "LED_0805":     0,
    "C_0402":       0,
    "C_0603":       0,
    "C_0805":       0,
    "C_1206":       0,
    "USB_C_GCT_USB4105":  180
  }
}
